mailbox_org_api/APIClient.py
mailbox_org_api/__init__.py
tests/__init__.py
tests/tests.py
mailbox_api_client_heshsum-0.1.dist-info/LICENSE
mailbox_api_client_heshsum-0.1.dist-info/METADATA
mailbox_api_client_heshsum-0.1.dist-info/WHEEL
mailbox_api_client_heshsum-0.1.dist-info/top_level.txt
mailbox_api_client_heshsum-0.1.dist-info/RECORD
