Metadata-Version: 2.1
Name: mailbox-api-client_heshsum
Version: 0.1
Summary: A library to access the mailbox.org Business API.
Author: Hendrik Schlange
Author-email: Hendrik Schlange <mail@heshsum.de>
Project-URL: Homepage, https://github.com/heshsum/mailbox-api-client
Project-URL: Issues, https://github.com/heshsum/mailbox-api-client/issues
Classifier: Programming Language :: Python :: 3
Classifier: License :: OSI Approved :: MIT License
Classifier: Operating System :: OS Independent
Requires-Python: >=3.8
License-File: LICENSE
